deluge_compat/__init__.py
deluge_compat/cli.py
deluge_compat/cli_chat.py
deluge_compat/functions.py
deluge_compat/py.typed
deluge_compat/runtime.py
deluge_compat/translator.py
deluge_compat/types.py
deluge_compat/zoho_namespace.py
deluge_compat/salesiq/__init__.py
deluge_compat/salesiq/core.py
deluge_compat/salesiq/functions.py
deluge_compat/salesiq/mocks.py
deluge_compat-1.2.11.dist-info/METADATA
deluge_compat-1.2.11.dist-info/WHEEL
deluge_compat-1.2.11.dist-info/entry_points.txt
deluge_compat-1.2.11.dist-info/licenses/LICENSE
deluge_compat-1.2.11.dist-info/RECORD
