Metadata-Version: 2.4
Name: deluge-compat
Version: 1.2.11
Summary: Python compatibility layer for executing Deluge scripts with full SalesIQ/Zobot support
Project-URL: Homepage, https://github.com/jctosta/deluge-compat
Project-URL: Repository, https://github.com/jctosta/deluge-compat
Project-URL: Issues, https://github.com/jctosta/deluge-compat/issues
Project-URL: Documentation, https://github.com/jctosta/deluge-compat/tree/main/docs
Author-email: Carlos Tosta <jctosta86@gmail.com>
License: MIT License
License-File: LICENSE
Keywords: compatibility,deluge,salesiq,scripting,zobot,zoho
Classifier: Development Status :: 4 - Beta
Classifier: Intended Audience :: Developers
Classifier: License :: OSI Approved :: MIT License
Classifier: Operating System :: OS Independent
Classifier: Programming Language :: Python :: 3
Classifier: Programming Language :: Python :: 3.10
Classifier: Programming Language :: Python :: 3.11
Classifier: Programming Language :: Python :: 3.12
Classifier: Topic :: Software Development :: Libraries :: Python Modules
Classifier: Topic :: Software Development :: Testing
Requires-Python: >=3.10
Requires-Dist: cryptography>=3.0.0
Requires-Dist: requests>=2.25.0
Provides-Extra: cli
Requires-Dist: faker>=24.0.0; extra == 'cli'
Requires-Dist: rich>=13.0.0; extra == 'cli'
Requires-Dist: typer>=0.9.0; extra == 'cli'
Provides-Extra: dev
Requires-Dist: pre-commit>=3.0.0; extra == 'dev'
Requires-Dist: pyright>=1.1.0; extra == 'dev'
Requires-Dist: pytest-cov>=4.0.0; extra == 'dev'
Requires-Dist: pytest>=7.0.0; extra == 'dev'
Requires-Dist: ruff>=0.1.0; extra == 'dev'
Provides-Extra: slim
